<?xml version="1.0" encoding="utf-8"?>
<abapGit version="v1.0.0" serializer="LCL_OBJECT_SPRX" serializer_version="v1.0.0">
 <asx:abap xmlns:asx="http://www.sap.com/abapxml" version="1.0">
  <asx:values>
   <PROXY_HEADER>
    <item>
     <OBJECT>TABL</OBJECT>
     <OBJ_NAME>ZVIESCHECK_VAT_REQUEST</OBJ_NAME>
     <OBJECT_M>TABL</OBJECT_M>
     <OBJ_NAME_M>ZVIESCHECK_VAT_REQUEST</OBJ_NAME_M>
     <HASH_ID>A4E2670BF2412BC89683E34D144575471281A6BF</HASH_ID>
     <ID>&lt;message&gt; checkVatRequest urn:ec.europa.eu:taxud:vies:services:checkVat urn:ec.europa.eu:taxud:vies:services:checkVat</ID>
     <IFR_GLOBAL>X</IFR_GLOBAL>
     <IFR_TYPE>message</IFR_TYPE>
     <IFR_NAME>checkVatRequest</IFR_NAME>
     <IFR_NSPCE>urn:ec.europa.eu:taxud:vies:services:checkVat</IFR_NSPCE>
     <IFR_GNSPCE>urn:ec.europa.eu:taxud:vies:services:checkVat</IFR_GNSPCE>
     <GEN_VERS>0006</GEN_VERS>
     <PREFIX>ZVIES</PREFIX>
     <CATEGORY>ifmmessage</CATEGORY>
     <GEN_APPL>WEBSERVICES</GEN_APPL>
     <X-ML_NSPCE>urn:ec.europa.eu:taxud:vies:services:checkVat:types</X-ML_NSPCE>
     <X-ML_NAME>checkVat</X-ML_NAME>
    </item>
   </PROXY_HEADER>
   <PROXY_DATA>
    <item>
     <OBJECT>TABL</OBJECT>
     <OBJ_NAME>ZVIESCHECK_VAT_REQUEST</OBJ_NAME>
     <OBJECT1>FIEL</OBJECT1>
     <OBJ_NAME1>COUNTRY_CODE</OBJ_NAME1>
     <OBJECT2>FIEL</OBJECT2>
     <OBJ_NAME2>COUNTRY_CODE</OBJ_NAME2>
     <ID>&lt;element&gt; {urn:ec.europa.eu:taxud:vies:services:checkVat:types}countryCode &lt;message&gt; checkVatRequest urn:ec.europa.eu:taxud:vies:services:checkVat urn:ec.europa.eu:taxud:vies:services:checkVat</ID>
     <IFR_TYPE>element</IFR_TYPE>
     <IFR_NAME>countryCode</IFR_NAME>
     <IFR_TAGTYP>E</IFR_TAGTYP>
     <IFR_MINOCC>1</IFR_MINOCC>
     <IFR_MAXOCC>1</IFR_MAXOCC>
     <IFR_QUALIF>X</IFR_QUALIF>
     <IFR_XSDTYP>string</IFR_XSDTYP>
     <IFR_SCALE>-2</IFR_SCALE>
     <R3_TYPE>FIEL</R3_TYPE>
     <R3_NAME>COUNTRY_CODE</R3_NAME>
     <R3_DATATYP>STRG</R3_DATATYP>
     <R3_SEQNUM>000001</R3_SEQNUM>
    </item>
    <item>
     <OBJECT>TABL</OBJECT>
     <OBJ_NAME>ZVIESCHECK_VAT_REQUEST</OBJ_NAME>
     <OBJECT1>FIEL</OBJECT1>
     <OBJ_NAME1>VAT_NUMBER</OBJ_NAME1>
     <OBJECT2>FIEL</OBJECT2>
     <OBJ_NAME2>VAT_NUMBER</OBJ_NAME2>
     <ID>&lt;element&gt; {urn:ec.europa.eu:taxud:vies:services:checkVat:types}vatNumber &lt;message&gt; checkVatRequest urn:ec.europa.eu:taxud:vies:services:checkVat urn:ec.europa.eu:taxud:vies:services:checkVat</ID>
     <IFR_TYPE>element</IFR_TYPE>
     <IFR_NAME>vatNumber</IFR_NAME>
     <IFR_TAGTYP>E</IFR_TAGTYP>
     <IFR_MINOCC>1</IFR_MINOCC>
     <IFR_MAXOCC>1</IFR_MAXOCC>
     <IFR_QUALIF>X</IFR_QUALIF>
     <IFR_XSDTYP>string</IFR_XSDTYP>
     <IFR_SCALE>-2</IFR_SCALE>
     <R3_TYPE>FIEL</R3_TYPE>
     <R3_NAME>VAT_NUMBER</R3_NAME>
     <R3_DATATYP>STRG</R3_DATATYP>
     <R3_SEQNUM>000002</R3_SEQNUM>
    </item>
    <item>
     <OBJECT>TABL</OBJECT>
     <OBJ_NAME>ZVIESCHECK_VAT_REQUEST</OBJ_NAME>
     <OBJECT1>TABL</OBJECT1>
     <OBJ_NAME1>ZVIESCHECK_VAT_REQUEST</OBJ_NAME1>
     <OBJECT2>TABL</OBJECT2>
     <OBJ_NAME2>ZVIESCHECK_VAT_REQUEST</OBJ_NAME2>
     <ID>&lt;message&gt; checkVatRequest urn:ec.europa.eu:taxud:vies:services:checkVat urn:ec.europa.eu:taxud:vies:services:checkVat</ID>
     <IFR_TYPE>message</IFR_TYPE>
     <IFR_NAME>checkVatRequest</IFR_NAME>
     <IFR_SCALE>-2</IFR_SCALE>
     <R3_TYPE>TABL</R3_TYPE>
     <R3_NAME>ZVIESCHECK_VAT_REQUEST</R3_NAME>
     <R3_TEXT>Proxy Structure (generated)</R3_TEXT>
     <CATEGORY>ifmmessage</CATEGORY>
    </item>
   </PROXY_DATA>
  </asx:values>
 </asx:abap>
</abapGit>
